fqr/__init__.py
fqr/cli/__init__.py
fqr/cli/cfg.py
fqr/cli/lib.py
fqr/cli/obj.py
fqr/cli/utl.py
fqr/core/__init__.py
fqr/core/cfg.py
fqr/core/enm.py
fqr/core/exc.py
fqr/core/lib.py
fqr/core/codecs/__init__.py
fqr/core/codecs/cfg.py
fqr/core/codecs/enm.py
fqr/core/codecs/lib.py
fqr/core/codecs/typ.py
fqr/core/codecs/utl.py
fqr/core/strings/__init__.py
fqr/core/strings/cfg.py
fqr/core/strings/enm.py
fqr/core/strings/exc.py
fqr/core/strings/lib.py
fqr/core/strings/obj.py
fqr/core/strings/typ.py
fqr/core/strings/utl.py
fqr/core/typ/__init__.py
fqr/core/typ/cfg.py
fqr/core/typ/lib.py
fqr/core/typ/obj.py
fqr/core/typ/typ.py
fqr/core/typ/utl/__init__.py
fqr/core/typ/utl/check.py
fqr/core/typ/utl/hint.py
fqr/docs/__init__.py
fqr/docs/cfg.py
fqr/docs/enm.py
fqr/docs/lib.py
fqr/docs/obj.py
fqr/docs/utl.py
fqr/docs/static/__init__.py
fqr/docs/static/conf.tpl
fqr/docs/static/favicon.ico
fqr/docs/static/logo.png
fqr/loggers/__init__.py
fqr/loggers/cfg.py
fqr/loggers/exc.py
fqr/loggers/lib.py
fqr/loggers/obj.py
fqr/loggers/typ.py
fqr/loggers/utl.py
fqr/objects/__init__.py
fqr/objects/cfg.py
fqr/objects/enm.py
fqr/objects/exc.py
fqr/objects/lib.py
fqr/objects/typ.py
fqr/objects/utl.py
fqr/objects/fields/__init__.py
fqr/objects/fields/obj.py
fqr/objects/metas/__init__.py
fqr/objects/metas/obj.py
fqr/objects/metas/utl.py
fqr/objects/objs/__init__.py
fqr/objects/objs/obj.py
fqr/objects/queries/__init__.py
fqr/objects/queries/obj.py
tests/__init__.py
tests/readme_test.py
tests/ci/__init__.py
tests/ci/cfg.py
tests/ci/commit_msg_test.py
tests/core/__init__.py
tests/core/cfg.py
tests/core/codecs/__init__.py
tests/core/codecs/cfg.py
tests/core/codecs/utl_test.py
tests/core/strings/__init__.py
tests/core/strings/cfg.py
tests/core/strings/exc_test.py
tests/core/strings/utl_test.py
tests/core/typings/__init__.py
tests/core/typings/cfg.py
tests/core/typings/utl_test.py
tests/loggers/__init__.py
tests/loggers/backup.py
tests/loggers/cfg.py
tests/loggers/exc_test.py
tests/loggers/obj_test.py
fqr-0.7.0.dist-info/LICENSE
fqr-0.7.0.dist-info/METADATA
fqr-0.7.0.dist-info/WHEEL
fqr-0.7.0.dist-info/entry_points.txt
fqr-0.7.0.dist-info/top_level.txt
fqr-0.7.0.dist-info/RECORD
