Metadata-Version: 2.1
Name: fqr
Version: 0.7.0
Summary: Zero-dependency Python framework for object oriented development.
Author-email: Dan <dan@1howardcapital.com>
Maintainer-email: Dan <dan@1howardcapital.com>
Project-URL: Documentation, https://fqr.readthedocs.io/en/stable/fqr.html
Project-URL: Homepage, https://fqr.readthedocs.io/en/stable/
Project-URL: Repository, https://github.com/dan1hc/fqr.git
Project-URL: Issues, https://github.com/dan1hc/fqr/issues
Project-URL: Changelog, https://github.com/dan1hc/fqr/blob/main/CHANGELOG.md
Keywords: dataclasses,fqr,framework,openapi,rest,swagger
Classifier: Development Status :: 3 - Alpha
Classifier: License :: OSI Approved :: GNU Library or Lesser General Public License (LGPL)
Classifier: Operating System :: OS Independent
Classifier: Programming Language :: Python :: 3.11
Classifier: Programming Language :: Python :: 3.12
Classifier: Topic :: Software Development :: Libraries :: Application Frameworks
Classifier: Typing :: Typed
Requires-Python: >=3.10
License-File: LICENSE
Requires-Dist: typing-extensions ; python_version < "3.11"
Provides-Extra: develop
Requires-Dist: mypy ==1.11.* ; extra == 'develop'
Requires-Dist: pre-commit ==3.6.* ; extra == 'develop'
Requires-Dist: coverage ==7.4.* ; extra == 'develop'
Requires-Dist: pytest ==7.4.* ; extra == 'develop'
Requires-Dist: pytest-cov ==4.1.* ; extra == 'develop'
Requires-Dist: ruff ==0.5.* ; extra == 'develop'
Requires-Dist: commonmark ==0.9.* ; extra == 'develop'
Requires-Dist: sphinx ==7.* ; extra == 'develop'
Provides-Extra: docs
Requires-Dist: commonmark ==0.9.* ; extra == 'docs'
Requires-Dist: sphinx ==7.* ; extra == 'docs'
